taurex_petitrad/__init__.py
taurex_petitrad/model/__init__.py
taurex_petitrad/model/directimage.py
taurex_petitrad/model/emission.py
taurex_petitrad/model/petitradtrans.py
taurex_petitrad/model/transmission.py
taurex_petitrad/opacities/__init__.py
taurex_petitrad/opacities/ck.py
taurex_petitrad/opacities/linebyline.py
taurex_petitrad/util/__init__.py
taurex_petitrad/util/moleculepath.py
taurex_petitrad-0.3.0a0.dist-info/LICENSE
taurex_petitrad-0.3.0a0.dist-info/METADATA
taurex_petitrad-0.3.0a0.dist-info/WHEEL
taurex_petitrad-0.3.0a0.dist-info/entry_points.txt
taurex_petitrad-0.3.0a0.dist-info/top_level.txt
taurex_petitrad-0.3.0a0.dist-info/RECORD
