Metadata-Version: 2.1
Name: taurex-petitrad
Version: 0.3.0a0
Summary: petitRADTRANS plugin for TauREx-3 
Home-page: UNKNOWN
Author: Ahmed Faris Al-Refaie
Author-email: ahmed.al-refaie.12@ucl.ac.uk
License: BSD
Keywords: exoplanet,petitradtrans,taurex,chemistrytaurex,plugin,taurex3,petitradtrans,atmosphere,atmospheric
Platform: UNKNOWN
Provides: taurex_petitrad
Requires-Dist: taurex
